cfn_lsp_extra/__init__.py
cfn_lsp_extra/__main__.py
cfn_lsp_extra/aws_data.py
cfn_lsp_extra/cfnlint_integration.py
cfn_lsp_extra/completions/__init__.py
cfn_lsp_extra/completions/allowed_values.py
cfn_lsp_extra/completions/attributes.py
cfn_lsp_extra/completions/functions.py
cfn_lsp_extra/completions/py.typed
cfn_lsp_extra/completions/ref.py
cfn_lsp_extra/completions/resources.py
cfn_lsp_extra/completions/static.py
cfn_lsp_extra/config/__init__.py
cfn_lsp_extra/config/py.typed
cfn_lsp_extra/config/user_configuration.py
cfn_lsp_extra/context.py
cfn_lsp_extra/cursor.py
cfn_lsp_extra/decode/__init__.py
cfn_lsp_extra/decode/extractors.py
cfn_lsp_extra/decode/json_decoding.py
cfn_lsp_extra/decode/position.py
cfn_lsp_extra/decode/py.typed
cfn_lsp_extra/decode/yaml_decoding.py
cfn_lsp_extra/definitions/__init__.py
cfn_lsp_extra/definitions/attributes.py
cfn_lsp_extra/definitions/py.typed
cfn_lsp_extra/definitions/ref.py
cfn_lsp_extra/hovers/__init__.py
cfn_lsp_extra/hovers/attributes.py
cfn_lsp_extra/hovers/functions.py
cfn_lsp_extra/hovers/py.typed
cfn_lsp_extra/hovers/refs.py
cfn_lsp_extra/intrinsic_functions.py
cfn_lsp_extra/py.typed
cfn_lsp_extra/ref.py
cfn_lsp_extra/resources/__init__.py
cfn_lsp_extra/resources/context.json
cfn_lsp_extra/resources/custom.json
cfn_lsp_extra/resources/doc_urls
cfn_lsp_extra/resources/sam_context.json
cfn_lsp_extra/resources/sam_doc_urls
cfn_lsp_extra/scrape/__init__.py
cfn_lsp_extra/scrape/markdown_textwrapper.py
cfn_lsp_extra/scrape/py.typed
cfn_lsp_extra/scrape/sam_specification.py
cfn_lsp_extra/scrape/specification.py
cfn_lsp_extra/scrape/with_success_failure_count.py
cfn_lsp_extra/server.py
cfn_lsp_extra-0.7.4.dist-info/LICENSE
cfn_lsp_extra-0.7.4.dist-info/METADATA
cfn_lsp_extra-0.7.4.dist-info/WHEEL
cfn_lsp_extra-0.7.4.dist-info/entry_points.txt
cfn_lsp_extra-0.7.4.dist-info/RECORD
