Metadata-Version: 2.3
Name: cfn-lsp-extra
Version: 0.7.4
Summary: Cfn Lsp Extra
License: MIT
Author: Laurence Warne
Author-email: laurencewarne@gmail.com
Requires-Python: >=3.9,<4
Classifier: Topic :: Software Development
Provides-Extra: parse
Requires-Dist: PyYAML (>=6.0.2,<7.0.0)
Requires-Dist: attrs (>=24.2,<26.0)
Requires-Dist: aws-sam-translator (>=1.96.0)
Requires-Dist: beautifulsoup4 (>=4.12.3,<5.0.0) ; extra == "parse"
Requires-Dist: botocore (>=1.35.81)
Requires-Dist: cfn-lint (>=1.32.4,<2.0.0)
Requires-Dist: click (>=8.1.7,<9.0.0)
Requires-Dist: importlib_resources (>=6.4.0)
Requires-Dist: lxml (>=5.2.1,<6.0.0) ; extra == "parse"
Requires-Dist: markdownify (>=0.12.1,<0.15.0) ; extra == "parse"
Requires-Dist: platformdirs (>=4.3.6)
Requires-Dist: pygls (>=1.3.1,<2.0.0)
Requires-Dist: requests (>=2.32.3,<3.0.0) ; extra == "parse"
Requires-Dist: types-PyYAML (>=6.0.2,<7.0.0)
Requires-Dist: types-beautifulsoup4 (>=4.12.0,<5.0.0) ; extra == "parse"
Requires-Dist: types-requests (>2,<3.0.0) ; extra == "parse"
Project-URL: Changelog, https://github.com/laurencewarne/cfn-lsp-extra/blob/master/CHANGELOG.md
Project-URL: Documentation, https://github.com/laurencewarne/cfn-lsp-extra/blob/master/README.md
Project-URL: Homepage, https://github.com/laurencewarne/cfn-lsp-extra
Project-URL: Issues, https://github.com/laurencewarne/cfn-lsp-extra/issues
Project-URL: Repository, https://github.com/laurencewarne/cfn-lsp-extra
